crczp/openstack_driver/__init__.py
crczp/openstack_driver/decorators.py
crczp/openstack_driver/open_stack_client.py
crczp/openstack_driver/open_stack_proxy.py
crczp/openstack_driver/utils.py
crczp/openstack_driver/templates/terraform-deploy-template.j2
crczp/openstack_driver/templates/terraform-provider-template.j2
crczp_openstack_lib-1.0.1.dist-info/METADATA
crczp_openstack_lib-1.0.1.dist-info/WHEEL
crczp_openstack_lib-1.0.1.dist-info/licenses/LICENSE
crczp_openstack_lib-1.0.1.dist-info/RECORD
